{
  "private": true,
  "scripts": {
    "jspsych": "jspsych -e <%= experiment %>",
    "start": "npm run jspsych -- run",
    "build": "npm run jspsych -- build",
    "jatos": "npm run jspsych -- build --jatos"
  },
  "dependencies": {
    "jspsych": "^7.3.1",
    "@jspsych/plugin-fullscreen": "^1.1.2",
    "@jspsych/plugin-html-keyboard-response": "^1.1.2",
    "@jspsych/plugin-preload": "^1.1.2"
  },
  "devDependencies": {
    "jspsych-builder": "^<%= builderVersion %>"
  },
  "browserslist": ">0.25%, not dead"
}
